lean_lldb.py
lean_lldb-0.1.0.dist-info/LICENSE
lean_lldb-0.1.0.dist-info/METADATA
lean_lldb-0.1.0.dist-info/WHEEL
lean_lldb-0.1.0.dist-info/RECORD
