Metadata-Version: 2.1
Name: lean-lldb
Version: 0.1.0
Summary: An LLDB extension for debugging Lean programs
Home-page: https://github.com/ydewit/lean-lldb
License: Apache-2.0
Keywords: debugging,lldb,lean
Author: Yuri de Wit
Author-email: ydewit@gmail.com
Requires-Python: >=3.7,<4.0
Classifier: License :: OSI Approved :: Apache Software License
Classifier: Programming Language :: Python :: 3
Classifier: Programming Language :: Python :: 3.7
Classifier: Programming Language :: Python :: 3.8
Classifier: Programming Language :: Python :: 3.9
Classifier: Programming Language :: Python :: 3.10
Classifier: Programming Language :: Python :: 3.11
Classifier: Programming Language :: Python :: 3.12
Requires-Dist: six (>=1.0.0,<2.0.0)
Project-URL: Repository, https://github.com/ydewit/lean-lldb
